rtfs/__init__.py
rtfs/build_scopes.py
rtfs/chunk_resolution/__init__.py
rtfs/chunk_resolution/chunk_graph.py
rtfs/chunk_resolution/cluster.py
rtfs/chunk_resolution/graph.py
rtfs/cli.py
rtfs/config.py
rtfs/file_resolution/__init__.py
rtfs/file_resolution/file_graph.py
rtfs/fs.py
rtfs/graph.py
rtfs/languages/__init__.py
rtfs/languages/python/__init__.py
rtfs/languages/python/generate_sys_modules.py
rtfs/languages/python/libs/my-python.exp
rtfs/languages/python/libs/my-python.lib
rtfs/languages/python/libs/my-python.so
rtfs/languages/python/python.py
rtfs/languages/python/python.scm
rtfs/languages/python/python_refs.scm
rtfs/languages/python/sys_modules.html
rtfs/languages/python/sys_modules.json
rtfs/moatless/__init__.py
rtfs/moatless/codeblocks.py
rtfs/moatless/epic_split.py
rtfs/moatless/module.py
rtfs/moatless/node_types.py
rtfs/moatless/parser/__init__.py
rtfs/moatless/parser/comment.py
rtfs/moatless/parser/create.py
rtfs/moatless/parser/java.py
rtfs/moatless/parser/parser.py
rtfs/moatless/parser/python.py
rtfs/moatless/parser/queries/__init__.py
rtfs/moatless/parser/queries/java.scm
rtfs/moatless/parser/queries/python.scm
rtfs/moatless/parser/queries/python_gpt.scm
rtfs/moatless/settings.py
rtfs/models.py
rtfs/repo_resolution/__init__.py
rtfs/repo_resolution/exports.py
rtfs/repo_resolution/graph_type.py
rtfs/repo_resolution/imports.py
rtfs/repo_resolution/module.py
rtfs/repo_resolution/namespace.py
rtfs/repo_resolution/repo_graph.py
rtfs/scope_resolution/__init__.py
rtfs/scope_resolution/call.py
rtfs/scope_resolution/capture_refs.py
rtfs/scope_resolution/definition.py
rtfs/scope_resolution/graph.py
rtfs/scope_resolution/graph_types.py
rtfs/scope_resolution/imports.py
rtfs/scope_resolution/interval_tree.py
rtfs/scope_resolution/reference.py
rtfs/scope_resolution/scope.py
rtfs/ts/__init__.py
rtfs/ts/capture_types.py
rtfs/utils.py
rtfs-0.1.1.dist-info/entry_points.txt
rtfs-0.1.1.dist-info/METADATA
rtfs-0.1.1.dist-info/WHEEL
rtfs-0.1.1.dist-info/RECORD
