Metadata-Version: 2.1
Name: rtfs
Version: 0.1.1
Summary: Code Repo Summary Generator
Author: John Peng
Author-email: kongyijipeng@gmail.com
Requires-Python: >=3.8,<4.0
Classifier: Programming Language :: Python :: 3
Classifier: Programming Language :: Python :: 3.8
Classifier: Programming Language :: Python :: 3.9
Classifier: Programming Language :: Python :: 3.10
Classifier: Programming Language :: Python :: 3.11
Classifier: Programming Language :: Python :: 3.12
Requires-Dist: PyYAML (==6.0.1)
Requires-Dist: anthropic (==0.32.0)
Requires-Dist: infomap (==2.8.0)
Requires-Dist: intervaltree (==3.1.0)
Requires-Dist: llama_index (==0.10.59)
Requires-Dist: networkx (==3.3)
Requires-Dist: openai (==1.38.0)
Requires-Dist: pydantic (==2.8.2)
Requires-Dist: python-dotenv (==1.0.1)
Requires-Dist: setuptools (==70.1.1)
Requires-Dist: simple_parsing (==0.1.5)
Requires-Dist: starlette (==0.38.2)
Requires-Dist: tenacity (==8.5.0)
Requires-Dist: tiktoken (==0.7.0)
Requires-Dist: tree_sitter (==0.22.3)
Requires-Dist: tree_sitter_java (==0.21.0)
Requires-Dist: tree_sitter_python (==0.21.0)
Requires-Dist: typing_extensions (==4.12.2)
